[
{ "_id" : { "$oid" : "642b657c601f3b2ee1a695f7" }, "taskId" : { "$oid" : "642b654a601f3b2ee1a6956c" }, "dayName" : "tuesday", "_date" : { "$date" : "2023-04-04T00:00:00.000+0000" }, "isComplete" : false, "employeeId" : null, "__v" : 0, "createdAt" : { "$date" : "2023-04-03T23:47:08.663+0000" }, "updatedAt" : { "$date" : "2023-04-03T23:47:08.663+0000" } },
{ "_id" : { "$oid" : "642b6844601f3b2ee1a6998f" }, "taskId" : { "$oid" : "642b654a601f3b2ee1a6956c" }, "dayName" : "monday", "_date" : { "$date" : "2023-04-03T23:59:00.298+0000" }, "isComplete" : false, "employeeId" : null, "__v" : 0, "createdAt" : { "$date" : "2023-04-03T23:59:00.337+0000" }, "updatedAt" : { "$date" : "2023-04-03T23:59:00.337+0000" } },
{ "_id" : { "$oid" : "642d02a3d048dab561a6b8f2" }, "taskId" : { "$oid" : "642b654a601f3b2ee1a6956c" }, "dayName" : "wednesday", "_date" : { "$date" : "2023-04-05T00:00:00.000+0000" }, "isComplete" : false, "employeeId" : null, "__v" : 0, "createdAt" : { "$date" : "2023-04-05T05:09:55.041+0000" }, "updatedAt" : { "$date" : "2023-04-05T05:09:55.041+0000" } },
{ "_id" : { "$oid" : "642e6bf2f5985cee61bfe61c" }, "taskId" : { "$oid" : "642b654a601f3b2ee1a6956c" }, "dayName" : "thursday", "_date" : { "$date" : "2023-04-06T00:00:00.000+0000" }, "isComplete" : false, "employeeId" : null, "__v" : 0, "createdAt" : { "$date" : "2023-04-06T06:51:30.389+0000" }, "updatedAt" : { "$date" : "2023-04-06T06:51:30.389+0000" } }
]
